mphops/__init__.py
mphops/__main__.py
mphops/daemon.py
mphops/forwarder_factory.py
mphops/multiproxy.py
mphops/parse_stream.py
mphops/remote_factory.py
mphops/server_factory.py
mphops/socks5_factory.py
mphops/start_proxy.py
mphops/util.py
mphops-0.0.7.dist-info/METADATA
mphops-0.0.7.dist-info/WHEEL
mphops-0.0.7.dist-info/entry_points.txt
mphops-0.0.7.dist-info/top_level.txt
mphops-0.0.7.dist-info/RECORD
