Metadata-Version: 2.1
Name: mphops
Version: 0.0.7
Summary: A simple proxy
Home-page: https://github.com/nyannko/twisted_proxy
Author: nyannko
Author-email: UNKNOWN
License: MIT Licence
Platform: any
Classifier: Programming Language :: Python :: 2
Classifier: License :: OSI Approved :: MIT License
Classifier: Operating System :: OS Independent
Requires-Dist: pyipv8 (==1.7.1)
